jsdfile/__init__.py
jsdfile/benchmark/__init__.py
jsdfile/benchmark/bench.py
jsdfile/benchmark/config.py
jsdfile/benchmark/utils.py
jsdfile/core/__init__.py
jsdfile/core/main.py
jsdfile/plot/__init__.py
jsdfile/plot/plot.py
jsdfile/plot/utility.py
jsdfile-0.1.0.dist-info/LICENSE
jsdfile-0.1.0.dist-info/METADATA
jsdfile-0.1.0.dist-info/WHEEL
jsdfile-0.1.0.dist-info/RECORD
