Metadata-Version: 2.3
Name: jsdfile
Version: 0.1.0
Summary: High-performance JSON serialization and deserialization library with efficient binary storage format. JSDFile combines msgspec speed with LZ4 compression for applications that need to store and retrieve JSON data rapidly while minimizing storage requirements.
License: MIT
Keywords: json,database,serialization,deserialization,compression,performance,msgspec,lz4,binary,file-format,data-storage,msgpack,high-performance,fast-json,io,persistence
Author: Alaamer
Author-email: ahmedmuhamed12@gmail.com
Maintainer: Alaamer
Maintainer-email: ahmedmuhamed239@gmail.com
Requires-Python: >=3.10,<4.0
Classifier: Development Status :: 4 - Beta
Classifier: Intended Audience :: Developers
Classifier: Intended Audience :: Information Technology
Classifier: Intended Audience :: System Administrators
Classifier: License :: OSI Approved :: MIT License
Classifier: Natural Language :: English
Classifier: Operating System :: OS Independent
Classifier: Programming Language :: Python
Classifier: Programming Language :: Python :: 3
Classifier: Programming Language :: Python :: 3.10
Classifier: Programming Language :: Python :: 3.11
Classifier: Programming Language :: Python :: 3.12
Classifier: Programming Language :: Python :: 3.13
Classifier: Programming Language :: Python :: Implementation :: CPython
Classifier: Topic :: Database
Classifier: Topic :: Internet :: WWW/HTTP :: Dynamic Content :: Content Management System
Classifier: Topic :: Software Development :: Libraries
Classifier: Topic :: Software Development :: Libraries :: Python Modules
Classifier: Topic :: Software Development :: Object Brokering
Classifier: Topic :: System :: Archiving :: Compression
Classifier: Topic :: System :: Filesystems
Classifier: Typing :: Typed
Requires-Dist: lz4 (>=4.4.4,<5.0.0)
Requires-Dist: msgspec (>=0.19.0,<0.20.0)
Project-URL: Documentation, https://github.com/alaamer12/jsdfile
Project-URL: Homepage, https://github.com/alaamer12/jsdfile
Project-URL: Repository, https://github.com/alaamer12/jsdfile
Project-URL: Source Code, https://github.com/alaamer12/jsdfile
